aws_runas/__init__.py
aws_runas/session_token_provider.py
aws_runas-0.2.0.dist-info/DESCRIPTION.rst
aws_runas-0.2.0.dist-info/METADATA
aws_runas-0.2.0.dist-info/RECORD
aws_runas-0.2.0.dist-info/WHEEL
aws_runas-0.2.0.dist-info/entry_points.txt
aws_runas-0.2.0.dist-info/metadata.json
aws_runas-0.2.0.dist-info/top_level.txt
