Metadata-Version: 2.0
Name: aws-runas
Version: 0.2.0
Summary: Execute a command using an AWS assumed role
Home-page: https://github.com/mmmorris1975/aws-runas
Author: Michael Morris
Author-email: mmmorris1975@netscape.net
License: MIT
Keywords: aws runas iam role
Platform: UNKNOWN
Classifier: Development Status :: 4 - Beta
Classifier: Intended Audience :: Developers
Classifier: Intended Audience :: System Administrators
Classifier: License :: OSI Approved :: MIT License
Classifier: Programming Language :: Python :: 2.7
Classifier: Programming Language :: Python :: 3
Requires-Python: >=2.7, <4
Requires-Dist: boto3 (>=1.3.1)
